seamsh/__init__.py
seamsh/_tools.py
seamsh/field.py
seamsh/geometry.py
seamsh/gmsh.py
seamsh/libseamsh.so
seamsh-0.4.18.dist-info/AUTHORS.txt
seamsh-0.4.18.dist-info/COPYING.txt
seamsh-0.4.18.dist-info/LICENSE.txt
seamsh-0.4.18.dist-info/METADATA
seamsh-0.4.18.dist-info/WHEEL
seamsh-0.4.18.dist-info/top_level.txt
seamsh-0.4.18.dist-info/RECORD
