Metadata-Version: 2.1
Name: seamsh
Version: 0.4.18
Summary: Ocean mesh generation
Home-page: https://git.immc.ucl.ac.be/jlambrechts/seamsh
Author: Jonathan Lambrechts
Author-email: jonathan.lambrechts@uclouvain.be
License: UNKNOWN
Platform: UNKNOWN
Classifier: Environment :: Console
Classifier: Development Status :: 4 - Beta
Classifier: License :: OSI Approved :: GNU General Public License v3 (GPLv3)
Classifier: Operating System :: POSIX :: Linux
Classifier: Operating System :: Microsoft :: Windows
Classifier: Operating System :: MacOS :: MacOS X
Classifier: Programming Language :: C
Classifier: Programming Language :: Python
Classifier: Topic :: Scientific/Engineering
Requires-Python: >=3.6
Requires-Dist: gdal (>=3.1.0)
Requires-Dist: gmsh
Requires-Dist: numpy
Requires-Dist: scipy
